qroissant-0.1.0.dist-info/METADATA
qroissant-0.1.0.dist-info/WHEEL
qroissant/__init__.py
qroissant/__init__.pyi
qroissant/py.typed
qroissant/qroissant.cpython-313-x86_64-linux-gnu.so
qroissant-0.1.0.dist-info/RECORD
